odoo9_addon_account_invoice_blocking-9.0.1.0.0.99.dev7-py2.7-nspkg.pth
odoo9_addon_account_invoice_blocking-9.0.1.0.0.99.dev7.dist-info/DESCRIPTION.rst
odoo9_addon_account_invoice_blocking-9.0.1.0.0.99.dev7.dist-info/METADATA
odoo9_addon_account_invoice_blocking-9.0.1.0.0.99.dev7.dist-info/RECORD
odoo9_addon_account_invoice_blocking-9.0.1.0.0.99.dev7.dist-info/WHEEL
odoo9_addon_account_invoice_blocking-9.0.1.0.0.99.dev7.dist-info/metadata.json
odoo9_addon_account_invoice_blocking-9.0.1.0.0.99.dev7.dist-info/namespace_packages.txt
odoo9_addon_account_invoice_blocking-9.0.1.0.0.99.dev7.dist-info/top_level.txt
odoo_addons/account_invoice_blocking/README.rst
odoo_addons/account_invoice_blocking/__init__.py
odoo_addons/account_invoice_blocking/__openerp__.py
odoo_addons/account_invoice_blocking/i18n/account_invoice_blocking.pot
odoo_addons/account_invoice_blocking/i18n/ar.po
odoo_addons/account_invoice_blocking/i18n/bg.po
odoo_addons/account_invoice_blocking/i18n/bs.po
odoo_addons/account_invoice_blocking/i18n/ca.po
odoo_addons/account_invoice_blocking/i18n/cs.po
odoo_addons/account_invoice_blocking/i18n/de.po
odoo_addons/account_invoice_blocking/i18n/el_GR.po
odoo_addons/account_invoice_blocking/i18n/en_GB.po
odoo_addons/account_invoice_blocking/i18n/es.po
odoo_addons/account_invoice_blocking/i18n/es_CR.po
odoo_addons/account_invoice_blocking/i18n/es_EC.po
odoo_addons/account_invoice_blocking/i18n/es_MX.po
odoo_addons/account_invoice_blocking/i18n/es_PE.po
odoo_addons/account_invoice_blocking/i18n/et.po
odoo_addons/account_invoice_blocking/i18n/fi.po
odoo_addons/account_invoice_blocking/i18n/fr.po
odoo_addons/account_invoice_blocking/i18n/fr_CA.po
odoo_addons/account_invoice_blocking/i18n/fr_CH.po
odoo_addons/account_invoice_blocking/i18n/gl.po
odoo_addons/account_invoice_blocking/i18n/hr.po
odoo_addons/account_invoice_blocking/i18n/hr_HR.po
odoo_addons/account_invoice_blocking/i18n/hu.po
odoo_addons/account_invoice_blocking/i18n/id.po
odoo_addons/account_invoice_blocking/i18n/it.po
odoo_addons/account_invoice_blocking/i18n/ja.po
odoo_addons/account_invoice_blocking/i18n/lt.po
odoo_addons/account_invoice_blocking/i18n/mk.po
odoo_addons/account_invoice_blocking/i18n/mn.po
odoo_addons/account_invoice_blocking/i18n/nb.po
odoo_addons/account_invoice_blocking/i18n/nb_NO.po
odoo_addons/account_invoice_blocking/i18n/nl.po
odoo_addons/account_invoice_blocking/i18n/nl_BE.po
odoo_addons/account_invoice_blocking/i18n/nl_NL.po
odoo_addons/account_invoice_blocking/i18n/pl.po
